<?xml version="1.0" encoding="UTF-8" standalone="yes"?>
<p:sld xmlns:a="http://schemas.openxmlformats.org/drawingml/2006/main" xmlns:r="http://schemas.openxmlformats.org/officeDocument/2006/relationships" xmlns:p="http://schemas.openxmlformats.org/presentationml/2006/main"><p:cSld><p:spTree><p:nvGrpSpPr><p:cNvPr id="1" name=""/><p:cNvGrpSpPr/><p:nvPr/></p:nvGrpSpPr><p:grpSpPr><a:xfrm><a:off x="0" y="0"/><a:ext cx="0" cy="0"/><a:chOff x="0" y="0"/><a:chExt cx="0" cy="0"/></a:xfrm></p:grpSpPr><p:grpSp><p:nvGrpSpPr><p:cNvPr id="56" name="Group 56"/><p:cNvGrpSpPr/><p:nvPr/></p:nvGrpSpPr><p:grpSpPr><a:xfrm><a:off x="1773550" y="112914"/><a:ext cx="5596900" cy="6632172"/><a:chOff x="0" y="0"/><a:chExt cx="5596899" cy="6632171"/></a:xfrm></p:grpSpPr><p:pic><p:nvPicPr><p:cNvPr id="55" name="5cf5259e80a89a0ae785554243a47c58.jpg"/><p:cNvPicPr><a:picLocks noChangeAspect="1"/></p:cNvPicPr><p:nvPr/></p:nvPicPr><p:blipFill><a:blip r:embed="rId2"><a:extLst/></a:blip><a:stretch><a:fillRect/></a:stretch></p:blipFill><p:spPr><a:xfrm><a:off x="25400" y="25400"/><a:ext cx="5546100" cy="6581372"/></a:xfrm><a:prstGeom prst="rect"><a:avLst/></a:prstGeom><a:ln><a:noFill/></a:ln><a:effectLst/></p:spPr></p:pic><p:pic><p:nvPicPr><p:cNvPr id="54" name="Picture 53"/><p:cNvPicPr><a:picLocks/></p:cNvPicPr><p:nvPr/></p:nvPicPr><p:blipFill><a:blip r:embed="rId3"><a:extLst/></a:blip><a:stretch><a:fillRect/></a:stretch></p:blipFill><p:spPr><a:xfrm><a:off x="0" y="0"/><a:ext cx="5596900" cy="6632172"/></a:xfrm><a:prstGeom prst="rect"><a:avLst/></a:prstGeom><a:effectLst/></p:spPr></p:pic></p:grpSp></p:spTree></p:cSld><p:clrMapOvr><a:masterClrMapping/></p:clrMapOvr><p:transition spd="med"/></p:sld>